{"format": "torch", "nodes": [{"name": "linear_1", "id": 1495945663208, "class_name": "Linear(in_features=20, out_features=87, bias=True)", "parameters": [["weight", [87, 20]], ["bias", [87]]], "output_shape": [[118825, 87]], "num_parameters": [1740, 87]}, {"name": "selu", "id": 1496195423536, "class_name": "SELU()", "parameters": [], "output_shape": [[118825, 87]], "num_parameters": []}, {"name": "linear_2", "id": 1495945663320, "class_name": "Linear(in_features=87, out_features=20, bias=True)", "parameters": [["weight", [20, 87]], ["bias", [20]]], "output_shape": [[118825, 20]], "num_parameters": [1740, 20]}, {"name": "linear_3", "id": 1495945663544, "class_name": "Linear(in_features=20, out_features=20, bias=True)", "parameters": [["weight", [20, 20]], ["bias", [20]]], "output_shape": [[118825, 20]], "num_parameters": [400, 20]}, {"name": "linear_4", "id": 1496110081976, "class_name": "Linear(in_features=20, out_features=2, bias=True)", "parameters": [["weight", [2, 20]], ["bias", [2]]], "output_shape": [[118825, 2]], "num_parameters": [40, 2]}, {"name": "softmax", "id": 1496195423592, "class_name": "Softmax()", "parameters": [], "output_shape": [[118825, 2]], "num_parameters": []}], "edges": []}